poc-axi-stream/smol-consumer.v
module smolconsumer(
    clk,
    rst_n,
    vld,
    rdy,
    data
);
    input clk, rst_n;
    input [31:0] data;
    input vld;
    output reg rdy;

    always @ (posedge clk or negedge rst_n) begin
        if (!rst_n) begin
            // on a hardware reset, deassert rdy
            rdy <= 0;
        end else if (vld) begin
            $display("data processed = [%08h]", data);
            rdy <= 1;
        end
    end
endmodule

poc-axi-stream/smol-producer.v
module smolproducer(
    clk,
    rst_n,
    vld,
    rdy,
    next_data,
    data
);
    input clk;
    input rst_n;
    output reg vld;
    input rdy;
    output reg [31:0] next_data;
    output reg [31:0] data;

    always @ (posedge clk or negedge rst_n) begin
      if (!rst_n) begin
        // on a hardware reset, deassert vld
        vld <= 0;
        next_data <= 0;
      end 
      else if (!vld) begin
        vld <= 1;
        next_data <= next_data + 1;
        data <= next_data;
      end else if (vld && rdy) begin
        $display ("HANDSHAKE DONE");
        vld <= 0;
      end
    end

endmodule

poc-axi-stream/smol-tb.v
module smoltb;
  reg clk, rst_n;
  wire [31:0] data;
  wire vld;
  wire rdy;
  wire [31:0] next_data;

  initial begin
    clk = 0;
    forever #5 clk = ~clk;
  end

  initial begin
    rst_n = 0;
    repeat (5) @(posedge clk);
    rst_n = 1;
  end

  initial begin
    $dumpfile("wave.vcd");
    $dumpvars(0, smoltb);
    #500 $finish;
  end

  smolproducer prod_inst(
    .clk(clk),
    .rst_n(rst_n),
    .vld(vld),
    .rdy(rdy),
    .data(data),
    .next_data(next_data)
  );

  smolconsumer cons_inst(
    .clk(clk),
    .rst_n(rst_n),
    .vld(vld),
    .rdy(rdy),
    .data(data)
  );
endmodule

poc-axi-stream/wave.vcd
$date
	Fri Dec 26 00:09:13 2025
$end
$version
	Icarus Verilog
$end
$timescale
	1s
$end
$scope module smoltb $end
$var wire 1 ! vld $end
$var wire 1 " rdy $end
$var wire 32 # next_data [31:0] $end
$var wire 32 $ data [31:0] $end
$var reg 1 % clk $end
$var reg 1 & rst_n $end
$scope module cons_inst $end
$var wire 1 % clk $end
$var wire 1 & rst_n $end
$var wire 1 ! vld $end
$var wire 32 ' data [31:0] $end
$var reg 1 " rdy $end
$upscope $end
$scope module prod_inst $end
$var wire 1 % clk $end
$var wire 1 " rdy $end
$var wire 1 & rst_n $end
$var reg 32 ( data [31:0] $end
$var reg 32 ) next_data [31:0] $end
$var reg 1 ! vld $end
$upscope $end
$upscope $end
$enddefinitions $end
$comment Show the parameter values. $end
$dumpall
$end
#0
$dumpvars
b0 )
bx (
bx '
0&
0%
bx $
b0 #
0"
0!
$end
#5
1%
#10
0%
#15
1%
#20
0%
#25
1%
#30
0%
#35
1%
#40
0%
#45
b0 $
b0 '
b0 (
b1 #
b1 )
1!
1&
1%
#50
0%
#55
1"
1%
#60
0%
#65
0!
1%
#70
0%
#75
b1 $
b1 '
b1 (
b10 #
b10 )
1!
1%
#80
0%
#85
0!
1%
#90
0%
#95
b10 $
b10 '
b10 (
b11 #
b11 )
1!
1%
#100
0%
#105
0!
1%
#110
0%
#115
b11 $
b11 '
b11 (
b100 #
b100 )
1!
1%
#120
0%
#125
0!
1%
#130
0%
#135
b100 $
b100 '
b100 (
b101 #
b101 )
1!
1%
#140
0%
#145
0!
1%
#150
0%
#155
b101 $
b101 '
b101 (
b110 #
b110 )
1!
1%
#160
0%
#165
0!
1%
#170
0%
#175
b110 $
b110 '
b110 (
b111 #
b111 )
1!
1%
#180
0%
#185
0!
1%
#190
0%
#195
b111 $
b111 '
b111 (
b1000 #
b1000 )
1!
1%
#200
0%
#205
0!
1%
#210
0%
#215
b1000 $
b1000 '
b1000 (
b1001 #
b1001 )
1!
1%
#220
0%
#225
0!
1%
#230
0%
#235
b1001 $
b1001 '
b1001 (
b1010 #
b1010 )
1!
1%
#240
0%
#245
0!
1%
#250
0%
#255
b1010 $
b1010 '
b1010 (
b1011 #
b1011 )
1!
1%
#260
0%
#265
0!
1%
#270
0%
#275
b1011 $
b1011 '
b1011 (
b1100 #
b1100 )
1!
1%
#280
0%
#285
0!
1%
#290
0%
#295
b1100 $
b1100 '
b1100 (
b1101 #
b1101 )
1!
1%
#300
0%
#305
0!
1%
#310
0%
#315
b1101 $
b1101 '
b1101 (
b1110 #
b1110 )
1!
1%
#320
0%
#325
0!
1%
#330
0%
#335
b1110 $
b1110 '
b1110 (
b1111 #
b1111 )
1!
1%
#340
0%
#345
0!
1%
#350
0%
#355
b1111 $
b1111 '
b1111 (
b10000 #
b10000 )
1!
1%
#360
0%
#365
0!
1%
#370
0%
#375
b10000 $
b10000 '
b10000 (
b10001 #
b10001 )
1!
1%
#380
0%
#385
0!
1%
#390
0%
#395
b10001 $
b10001 '
b10001 (
b10010 #
b10010 )
1!
1%
#400
0%
#405
0!
1%
#410
0%
#415
b10010 $
b10010 '
b10010 (
b10011 #
b10011 )
1!
1%
#420
0%
#425
0!
1%
#430
0%
#435
b10011 $
b10011 '
b10011 (
b10100 #
b10100 )
1!
1%
#440
0%
#445
0!
1%
#450
0%
#455
b10100 $
b10100 '
b10100 (
b10101 #
b10101 )
1!
1%
#460
0%
#465
0!
1%
#470
0%
#475
b10101 $
b10101 '
b10101 (
b10110 #
b10110 )
1!
1%
#480
0%
#485
0!
1%
#490
0%
#495
b10110 $
b10110 '
b10110 (
b10111 #
b10111 )
1!
1%
